PyRoxy/__init__.py
PyRoxy/Exceptions/__init__.py
PyRoxy/GeoIP/__init__.py
PyRoxy/GeoIP/Sqlite/COPYRIGHT.txt
PyRoxy/GeoIP/Sqlite/GeoLite2-Country.mmdb
PyRoxy/GeoIP/Sqlite/LICENSE.txt
PyRoxy/Tools/__init__.py
pyroxy_real2-1.0b5.dist-info/licenses/LICENSE.md
pyroxy_real2-1.0b5.dist-info/METADATA
pyroxy_real2-1.0b5.dist-info/WHEEL
pyroxy_real2-1.0b5.dist-info/top_level.txt
pyroxy_real2-1.0b5.dist-info/RECORD
